MANIFEST.in
setup.py
anthill/__init__.py
anthill/store/__init__.py
anthill/store/handler.py
anthill/store/options.py
anthill/store/server.py
anthill/store/admin/__init__.py
anthill/store/admin/appstore.py
anthill/store/admin/mailru.py
anthill/store/admin/steam.py
anthill/store/admin/xsolla.py
anthill/store/model/__init__.py
anthill/store/model/campaign.py
anthill/store/model/category.py
anthill/store/model/item.py
anthill/store/model/order.py
anthill/store/model/store.py
anthill/store/model/tier.py
anthill/store/model/components/__init__.py
anthill/store/model/components/appstore.py
anthill/store/model/components/mailru.py
anthill/store/model/components/steam.py
anthill/store/model/components/xsolla.py
anthill/store/sql/campaign_items.sql
anthill/store/sql/campaigns.sql
anthill/store/sql/categories.sql
anthill/store/sql/categories_common.sql
anthill/store/sql/currencies.sql
anthill/store/sql/items.sql
anthill/store/sql/orders.sql
anthill/store/sql/store_components.sql
anthill/store/sql/stores.sql
anthill/store/sql/tier_components.sql
anthill/store/sql/tiers.sql
anthill_store.egg-info/PKG-INFO
anthill_store.egg-info/SOURCES.txt
anthill_store.egg-info/dependency_links.txt
anthill_store.egg-info/namespace_packages.txt
anthill_store.egg-info/not-zip-safe
anthill_store.egg-info/requires.txt
anthill_store.egg-info/top_level.txt