Metadata-Version: 1.0
Name: anthill-store
Version: 0.2
Summary: Monetization service for Anthill platform
Home-page: https://github.com/anthill-platform/anthill-store
Author: desertkun
Author-email: desertkun@gmail.com
License: MIT
Platform: UNKNOWN
